pyscaffoldext/django/__init__.py
pyscaffoldext/django/extension.py
pyscaffoldext/django/templates/__init__.py
pyscaffoldext/django/templates/manage.template
pyscaffoldext_django-0.2.dist-info/AUTHORS.rst
pyscaffoldext_django-0.2.dist-info/LICENSE.txt
pyscaffoldext_django-0.2.dist-info/METADATA
pyscaffoldext_django-0.2.dist-info/WHEEL
pyscaffoldext_django-0.2.dist-info/entry_points.txt
pyscaffoldext_django-0.2.dist-info/top_level.txt
pyscaffoldext_django-0.2.dist-info/RECORD
