Metadata-Version: 2.1
Name: pyscaffoldext-django
Version: 0.2
Summary: Integration of django builtin scaffold cli (django-admin) into PyScaffold
Home-page: https://gitub.com/pyscaffold/pyscaffoldext-django
Author: Anderson Bravalheri
Author-email: andersonbravalheri@gmail.com
License: MIT
Project-URL: Documentation, https://pyscaffoldext-django.readthedocs.io
Project-URL: Source, https://github.com/pyscaffold/pyscaffoldext-django
Project-URL: Tracker, https://github.com/pyscaffold/pyscaffoldext-django/issues
Project-URL: Download, https://pypi.org/project/pyscaffoldext-django/#files
Platform: any
Classifier: Development Status :: 4 - Beta
Classifier: Programming Language :: Python
Requires-Python: >=3.8
License-File: LICENSE.txt
License-File: AUTHORS.rst
Requires-Dist: pyscaffold (<5.0a0,>=4.0b4)
Requires-Dist: django (<5.0a0,>=4.0.3)
Provides-Extra: testing
Requires-Dist: tox ; extra == 'testing'
Requires-Dist: pre-commit ; extra == 'testing'
Requires-Dist: setuptools-scm ; extra == 'testing'
Requires-Dist: virtualenv ; extra == 'testing'
Requires-Dist: configupdater ; extra == 'testing'
Requires-Dist: pytest ; extra == 'testing'
Requires-Dist: pytest-cov ; extra == 'testing'
Requires-Dist: pytest-xdist ; extra == 'testing'
